[
{"symbol": "USD", "price": "1.1754"},
{"symbol": "JPY", "price": "128.64"},
{"symbol": "BGN", "price": "1.9558"},
{"symbol": "CZK", "price": "25.795"},
{"symbol": "DKK", "price": "7.4476"},
{"symbol": "GBP", "price": "0.87733"},
{"symbol": "HUF", "price": "319.70"},
{"symbol": "PLN", "price": "4.2793"},
{"symbol": "RON", "price": "4.6593"},
{"symbol": "SEK", "price": "10.2870"},
{"symbol": "CHF", "price": "1.1572"},
{"symbol": "ISK", "price": "124.70"},
{"symbol": "NOK", "price": "9.5085"},
{"symbol": "HRK", "price": "7.3830"},
{"symbol": "RUB", "price": "73.4773"},
{"symbol": "TRY", "price": "5.2798"},
{"symbol": "AUD", "price": "1.5496"},
{"symbol": "BRL", "price": "4.5149"},
{"symbol": "CAD", "price": "1.5274"},
{"symbol": "CNY", "price": "7.5333"},
{"symbol": "HKD", "price": "9.2222"},
{"symbol": "IDR", "price": "16373.32"},
{"symbol": "ILS", "price": "4.2009"},
{"symbol": "INR", "price": "79.3420"},
{"symbol": "KRW", "price": "1263.46"},
{"symbol": "MXN", "price": "24.0774"},
{"symbol": "MYR", "price": "4.6867"},
{"symbol": "NZD", "price": "1.6734"},
{"symbol": "PHP", "price": "62.068"},
{"symbol": "SGD", "price": "1.5702"},
{"symbol": "THB", "price": "37.683"},
{"symbol": "ZAR", "price": "15.3821"}
]